my_autopylot/__init__.py
my_autopylot/CheckSystem.py
my_autopylot/cli/__init__.py
my_autopylot/cli/ap_console.py
my_autopylot/cli/my_autopylot.py
my_autopylot/cli/speed_test.py
my_autopylot/CrashHandler.py
my_autopylot/Engine.py
my_autopylot/resources/__init__.py
my_autopylot/Toolkit.py
my_autopylot/Windows/functions/__init__.py
my_autopylot/Windows/functions/blackbox/__init__.py
my_autopylot/Windows/functions/blackbox/BlackBox.cp38-win_amd64.pyd
my_autopylot/Windows/functions/blackbox/BlackBox.cp39-win_amd64.pyd
my_autopylot/Windows/functions/chrome/__init__.py
my_autopylot/Windows/functions/chrome/chrome310.py
my_autopylot/Windows/functions/chrome/chrome37.py
my_autopylot/Windows/functions/chrome/chrome38.py
my_autopylot/Windows/functions/chrome/chrome39.py
my_autopylot/Windows/functions/excel/__init__.py
my_autopylot/Windows/functions/excel/excel310.py
my_autopylot/Windows/functions/excel/excel37.py
my_autopylot/Windows/functions/excel/excel38.py
my_autopylot/Windows/functions/excel/excel39.py
my_autopylot/Windows/functions/extras/__init__.py
my_autopylot/Windows/functions/extras/extras310.py
my_autopylot/Windows/functions/extras/extras37.py
my_autopylot/Windows/functions/extras/extras38.py
my_autopylot/Windows/functions/extras/extras39.py
my_autopylot/Windows/functions/folder/__init__.py
my_autopylot/Windows/functions/folder/folder310.py
my_autopylot/Windows/functions/folder/folder37.py
my_autopylot/Windows/functions/folder/folder38.py
my_autopylot/Windows/functions/folder/folder39.py
my_autopylot/Windows/functions/keyboard/__init__.py
my_autopylot/Windows/functions/keyboard/keyboard310.py
my_autopylot/Windows/functions/keyboard/keyboard37.py
my_autopylot/Windows/functions/keyboard/keyboard38.py
my_autopylot/Windows/functions/keyboard/keyboard39.py
my_autopylot/Windows/functions/mouse/__init__.py
my_autopylot/Windows/functions/mouse/mouse310.py
my_autopylot/Windows/functions/mouse/mouse37.py
my_autopylot/Windows/functions/mouse/mouse38.py
my_autopylot-0.0.6.dist-info/entry_points.txt
my_autopylot-0.0.6.dist-info/LICENSE
my_autopylot-0.0.6.dist-info/WHEEL
my_autopylot-0.0.6.dist-info/METADATA
my_autopylot-0.0.6.dist-info/RECORD
