Metadata-Version: 2.1
Name: my-autopylot
Version: 0.0.6
Summary: Auto-Pylot is a Python based RPA platform for Software BOT development as an Open Source project. We strive to liberate humans from mundane, repetitive tasks, giving them more time to use their intellect and creativity to solve higher-order business challenges and perform knowledge work. We see a world where every employee will work side by side with Digital Workers, taking the robot out of the human, making them exponentially more productive and far more fulfilled.
License: BSD
Keywords: PyBots,autopilot,auto pylot,RPA,Python,Automation,BOT,Software BOT,Auto Pilot,Dost
Author: PyBots
Author-email: support@pybots.ai
Requires-Python: >=3.8.0,<=3.9.40
Classifier: Development Status :: 4 - Beta
Classifier: Environment :: Console
Classifier: Environment :: Win32 (MS Windows)
Classifier: Framework :: Robot Framework
Classifier: Framework :: Robot Framework :: Library
Classifier: Framework :: Robot Framework :: Tool
Classifier: Intended Audience :: Developers
Classifier: Intended Audience :: Education
Classifier: Intended Audience :: End Users/Desktop
Classifier: Intended Audience :: Financial and Insurance Industry
Classifier: Intended Audience :: Information Technology
Classifier: Intended Audience :: System Administrators
Classifier: License :: OSI Approved :: BSD License
Classifier: License :: Other/Proprietary License
Classifier: Natural Language :: English
Classifier: Operating System :: Microsoft :: Windows
Classifier: Programming Language :: Python
Classifier: Programming Language :: Python :: 3
Classifier: Programming Language :: Python :: 3.8
Classifier: Programming Language :: Python :: 3.9
Classifier: Topic :: Home Automation
Classifier: Topic :: Software Development :: Build Tools
Requires-Dist: Pillow (>=9.0.1,<10.0.0)
Requires-Dist: PyGetWindow (>=0.0.9,<0.0.10)
Requires-Dist: PyScreeze (>=0.1.28,<0.2.0)
Requires-Dist: SpeechRecognition (>=3.8.1,<4.0.0)
Requires-Dist: colored (>=1.4.3,<2.0.0)
Requires-Dist: emoji (>=1.7.0,<2.0.0)
Requires-Dist: gTTS (>=2.2.3,<3.0.0)
Requires-Dist: helium (>=3.0.8,<4.0.0)
Requires-Dist: numpy (==1.21.5)
Requires-Dist: pandas (>=1.4.1,<2.0.0)
Requires-Dist: psutil (>=5.9.0,<6.0.0)
Requires-Dist: pyfiglet (>=0.8.post1,<0.9)
Requires-Dist: pyinspect (>=0.1.0,<0.2.0)
Requires-Dist: pywinauto (>=0.6.8,<0.7.0)
Requires-Dist: rich (>=11.2.0,<12.0.0)
Requires-Dist: speedtest-cli (>=2.1.3,<3.0.0)
Requires-Dist: webdriver-manager (>=3.5.3,<4.0.0)
Project-URL: Documentation, https://my-autopylot.readthedocs.io/
Project-URL: Date ❤️ with PyBots, https://sites.google.com/view/clointfusion-hackathon/date-with-clointfusion
Project-URL: WhatsApp Community, https://chat.whatsapp.com/JKr7m0avmkIFwYgMarShZG
